run_examples/__init__.py
run_examples/crosswalk_api_examples.py
run_examples/cui_api_examples.py
run_examples/search_api_examples.py
run_examples/semantic_api_examples.py
run_examples/source_api_examples.py
umls_python_client/__init__.py
umls_python_client/umls_client.py
umls_python_client/baseAPI/__init__.py
umls_python_client/baseAPI/umls_api_base.py
umls_python_client/crosswalkAPI/__init__.py
umls_python_client/crosswalkAPI/crosswalk_api.py
umls_python_client/cuiAPI/__init__.py
umls_python_client/cuiAPI/cui_api.py
umls_python_client/searchAPI/__init__.py
umls_python_client/searchAPI/search_api.py
umls_python_client/semanticNetworkAPI/__init__.py
umls_python_client/semanticNetworkAPI/semantic_network_api.py
umls_python_client/sourceAPI/__init__.py
umls_python_client/sourceAPI/source_api.py
umls_python_client/utils/__init__.py
umls_python_client/utils/json_to_rdf.py
umls_python_client/utils/relationship_labels.py
umls_python_client/utils/save_output.py
umls_python_client/utils/utils.py
umls_python_client-1.0.5.dist-info/LICENSE
umls_python_client-1.0.5.dist-info/METADATA
umls_python_client-1.0.5.dist-info/WHEEL
umls_python_client-1.0.5.dist-info/top_level.txt
umls_python_client-1.0.5.dist-info/RECORD
