Metadata-Version: 2.1
Name: umls-python-client
Version: 1.0.5
Summary: UMLS Client for interacting with UMLS APIs including Search, Source, CUI, Semantic Network, and Crosswalk APIs.
Home-page: https://palasht75.github.io/umls-python-client-homepage/
Author: Palash Thakur
Author-email: palasht75@gmail.com
License: Apache License 2.0
Project-URL: Source, https://github.com/palasht75/umls-python-client
Project-URL: Tracker, https://github.com/palasht75/umls-python-client/issues
Project-URL: Documentation, https://github.com/palasht75/umls-python-client
Keywords: UMLS,API client,Python,Unified Medical Language System,healthcare data,umls-python,umls-pyton-client,umls-client,umls-api,py-umls
Classifier: Programming Language :: Python :: 3.9
Classifier: License :: OSI Approved :: Apache Software License
Classifier: Operating System :: OS Independent
Classifier: Intended Audience :: Developers
Classifier: Intended Audience :: Science/Research
Classifier: Topic :: Software Development :: Libraries :: Python Modules
Classifier: Topic :: Scientific/Engineering :: Medical Science Apps.
Requires-Python: >=3.9
License-File: LICENSE
Requires-Dist: requests
Requires-Dist: rdflib
